{
  "objectInfo" : {
    "id" : "7EwuBZhQqSzh8A7j4z3TYg",
    "name" : "GIT_CI_PROJ_renamed",
    "type" : "Project",
    "metadata" : {
      "modelVersion" : {
        "major" : 0,
        "minor" : 0
      },
      "repoInfo" : null,
      "contextAttributes" : [ ],
      "additionalInfo" : {
        "description" : "Renamed proj",
        "contentType" : "Binary",
        "documentState" : "COMPLETE"
      }
    }
  },
  "dataFileExtension" : "json",
  "updateTime" : "2024-04-09T02:06:58.510Z",
  "objectRefs" : [ ]
}